kuzu/__init__.py
kuzu/_kuzu.cpython-39-aarch64-linux-gnu.so
kuzu/async_connection.py
kuzu/connection.py
kuzu/database.py
kuzu/prepared_statement.py
kuzu/py.typed
kuzu/query_result.py
kuzu/torch_geometric_feature_store.py
kuzu/torch_geometric_graph_store.py
kuzu/torch_geometric_result_converter.py
kuzu/types.py
kuzu-0.11.3.dist-info/METADATA
kuzu-0.11.3.dist-info/WHEEL
kuzu-0.11.3.dist-info/top_level.txt
kuzu-0.11.3.dist-info/zip-safe
kuzu-0.11.3.dist-info/RECORD
kuzu-0.11.3.dist-info/licenses/LICENSE
