Metadata-Version: 2.1
Name: kuzu
Version: 0.11.3
Summary: Highly scalable, extremely fast, easy-to-use embeddable graph database
Home-page: https://github.com/kuzudb/kuzu
License: MIT
Project-URL: Homepage, https://kuzudb.com/
Project-URL: Documentation, https://docs.kuzudb.com/
Project-URL: Repository, https://github.com/kuzudb/kuzu
Project-URL: Changelog, https://github.com/kuzudb/kuzu/releases
Keywords: graph,database
License-File: LICENSE
